{
  "product" : [
      {
          "id": "SKU-1",
          "name": "Canon EOS 5 DSLR Camera",
          "imgUrl": "https://i.ytimg.com/vi/IjwDe72W9Fg/maxresdefault.jpg",
          "stock" : 10,
          "description" : "The Canon EOS 5 is a semi-professional autofocus, autoexposure 35 mm SLR film camera.",
          "price" : 35000

      },
      {
          "id": "SKU-2",
          "name": "Canon EOS 6 DSLR Camera",
          "imgUrl": "https://m.media-amazon.com/images/I/71OJD9qlQyL._SL1500_.jpg",
          "stock" : 10,
          "description" : "The Canon EOS 6D is a light, full-frame DSLR, fitted with a 20.2 megapixel CMOS sensor, 11-point AutoFocus system and built-in GPS and Wi-Fi support.",
          "price" : 45000
      },
      {
        "id": "SKU-3",
        "name": "Canon EOS A2 Mirrorless Camera",
        "imgUrl": "https://global.canon/ja/c-museum/wp-content/uploads/2015/05/film159_b.jpg",
        "stock" : 0,
        "description" : "Canon EOS-A2 SLR 35mm FILM Camera with Tamron 80-210mm Lens w/Hood, Vertical Grip Here is great package that includes everything you need to start shooting ",
        "price" : 39000
    },
    {
      "id": "SKU-4",
      "name": "Canon Mark 5000D Mirrorless",
      "imgUrl": "https://global.canon/ja/c-museum/wp-content/uploads/2015/05/film159_b.jpg",
      "stock" : 15,
      "description" : "Canon Mark 5000D Mirrorless 35mm FILM Camera with Tamron 80-210mm Lens w/Hood, Vertical Grip Here is great package that includes everything you need to start shooting ",
      "price" : 390000
  },
  {
    "id": "SKU-5",
    "name": "Canon Mark 4000D Mirrorless",
    "imgUrl": "https://global.canon/ja/c-museum/wp-content/uploads/2015/05/film159_b.jpg",
    "stock" : 10,
    "description" : "Canon Mark 4000D Mirrorless 35mm FILM Camera with Tamron 80-210mm Lens w/Hood, Vertical Grip Here is great package that includes everything you need to start shooting ",
    "price" : 290000
}
  ]
}